pydrobert/speech/__init__.py
pydrobert/speech/_sphere.py
pydrobert/speech/_version.py
pydrobert/speech/alias.py
pydrobert/speech/command_line.py
pydrobert/speech/compute.py
pydrobert/speech/config.py
pydrobert/speech/corpus.py
pydrobert/speech/filters.py
pydrobert/speech/post.py
pydrobert/speech/pre.py
pydrobert/speech/scales.py
pydrobert/speech/util.py
pydrobert/speech/vis.py
pydrobert_speech-0.3.0.dist-info/LICENSE
pydrobert_speech-0.3.0.dist-info/LICENSE_sph2pipe
pydrobert_speech-0.3.0.dist-info/METADATA
pydrobert_speech-0.3.0.dist-info/WHEEL
pydrobert_speech-0.3.0.dist-info/entry_points.txt
pydrobert_speech-0.3.0.dist-info/top_level.txt
pydrobert_speech-0.3.0.dist-info/RECORD
