Metadata-Version: 2.1
Name: pydrobert-speech
Version: 0.3.0
Summary: "Utilities for the python package 'param'"
Home-page: https://github.com/sdrobert/pydrobert-speech
Author: Sean Robertson
Author-email: sdrobert@cs.toronto.edu
License: Apache-2.0
Project-URL: Documentation, https://pydrobert-speech.readthedocs.io
Classifier: Development Status :: 3 - Alpha
Classifier: License :: OSI Approved :: Apache Software License
Classifier: Programming Language :: Python :: 3
Requires-Python: >=3.7
License-File: LICENSE
License-File: LICENSE_sph2pipe
Requires-Dist: numpy
Provides-Extra: kaldi
Requires-Dist: pydrobert-kaldi ; extra == 'kaldi'
Provides-Extra: pytorch
Requires-Dist: pydrobert-pytorch ; extra == 'pytorch'
Provides-Extra: vis
Requires-Dist: matplotlib ; extra == 'vis'
